ghclone/__init__.py
ghclone/ghclone.py
ghclone-1.0.0.dist-info/entry_points.txt
ghclone-1.0.0.dist-info/LICENSE
ghclone-1.0.0.dist-info/WHEEL
ghclone-1.0.0.dist-info/METADATA
ghclone-1.0.0.dist-info/RECORD
