Metadata-Version: 2.1
Name: ghclone
Version: 1.0.0
Summary: A command line utility to interactively search and clone GitHub repositories
License: MIT
Author: Tibo Clausen
Author-email: tibo.clausen@gmail.com
Requires-Python: >=3.7,<4.0
Classifier: License :: OSI Approved :: MIT License
Classifier: Programming Language :: Python :: 3
Classifier: Programming Language :: Python :: 3.7
Classifier: Programming Language :: Python :: 3.8
Classifier: Programming Language :: Python :: 3.9
